jg_comp/__init__.py
jg_comp/compression_strategy.py
jg_comp/compressor.py
jg_comp/huffman.py
jg_comp/main.py
jg_comp/matching.py
jg_comp/utils.py
tests/__init__.py
tests/test_compressor.py
jg_comp-0.1.5.dist-info/METADATA
jg_comp-0.1.5.dist-info/WHEEL
jg_comp-0.1.5.dist-info/top_level.txt
jg_comp-0.1.5.dist-info/RECORD
